the_collector/__init__.py
the_collector/ver_1/bagit.py
the_collector/ver_1/data.py
the_collector/ver_1/extra_numpy.py
the_collector/ver_1/protocols.py
the_collector/ver_2/collector.py
the_collector-2023.8.26.dist-info/LICENSE
the_collector-2023.8.26.dist-info/METADATA
the_collector-2023.8.26.dist-info/WHEEL
the_collector-2023.8.26.dist-info/RECORD
