Metadata-Version: 2.1
Name: the-collector
Version: 2023.8.26
Summary: A library to store data in common formats
Home-page: https://pypi.org/project/the-collector/
License: MIT
Keywords: library,robotics,robot,storage,json,pickle,gzip,csv
Author: walchko
Author-email: walchko@users.noreply.github.com
Requires-Python: >=3.10
Classifier: Development Status :: 4 - Beta
Classifier: Intended Audience :: Developers
Classifier: License :: OSI Approved :: MIT License
Classifier: Operating System :: OS Independent
Classifier: Programming Language :: Python :: 3
Classifier: Programming Language :: Python :: 3.10
Classifier: Programming Language :: Python :: 3.11
Classifier: Topic :: Software Development :: Libraries
Classifier: Topic :: Software Development :: Libraries :: Application Frameworks
Classifier: Topic :: Software Development :: Libraries :: Python Modules
Project-URL: Repository, http://github.com/MomsFriendlyRobotCompany/the_collector
